starlingrt/__init__.py
starlingrt/data.py
starlingrt/functions.py
starlingrt/sample.py
starlingrt/visualize.py
starlingrt-0.1.0.dist-info/LICENSE.md
starlingrt-0.1.0.dist-info/METADATA
starlingrt-0.1.0.dist-info/WHEEL
starlingrt-0.1.0.dist-info/top_level.txt
starlingrt-0.1.0.dist-info/RECORD
