Metadata-Version: 2.1
Name: starlingrt
Version: 0.1.0
Summary: [I]nteractive [R]etention [T]ime vi[S]ualization for gas chromatography.
Author-email: "Nathan A. Mahynski" <nathan.mahynski@gmail.com>
Maintainer-email: "Nathan A. Mahynski" <nathan.mahynski@gmail.com>
License: # NIST Software Licensing Statement
Project-URL: Repository, https://github.com/mahynski/starlingrt.git
Project-URL: Documentation, https://starlingrt.readthedocs.io/
Project-URL: Issues, https://github.com/mahynski/starlingrt/issues
Classifier: Development Status :: 5 - Production/Stable
Classifier: Intended Audience :: Science/Research
Classifier: Operating System :: OS Independent
Classifier: Programming Language :: Python :: 3
Requires-Python: >=3.10
License-File: LICENSE.md
Requires-Dist: numpy <2.0.0,>=1.23
Requires-Dist: scipy
Requires-Dist: scikit-learn
Requires-Dist: matplotlib >=3.7.2
Requires-Dist: pandas ==2.2
Requires-Dist: bokeh ==3.0.3
Requires-Dist: xlrd ==2.0.1
Requires-Dist: pre-commit ==3.3.3
Requires-Dist: pytest >=7.4.0
Requires-Dist: ipykernel
Requires-Dist: mypy
Requires-Dist: sphinx
Provides-Extra: all
